<?xml version="1.0" encoding="UTF-8" standalone="yes" ?>
<Manifest class="java.util.jar.Manifest" ref-id="941489262">
   <xi:include xmlns:xi="http://www.w3.org/2001/XInclude" href="java/lang/Cloneable.xml"/>
   <implements interface="java.lang.Cloneable"/>
   <extends class="java.lang.Object"/>
   <xi:include xmlns:xi="http://www.w3.org/2001/XInclude" href="java/lang/StringBuffer.xml"/>
   <xi:include xmlns:xi="http://www.w3.org/2001/XInclude" href="java/lang/String.xml"/>
   <xi:include xmlns:xi="http://www.w3.org/2001/XInclude" href="java/io/OutputStream.xml"/>
   <xi:include xmlns:xi="http://www.w3.org/2001/XInclude" href="java/lang/Object.xml"/>
   <xi:include xmlns:xi="http://www.w3.org/2001/XInclude" href="java/util/Map.xml"/>
   <xi:include xmlns:xi="http://www.w3.org/2001/XInclude" href="java/util/jar/Attributes.xml"/>
   <xi:include xmlns:xi="http://www.w3.org/2001/XInclude" href="java/io/IOException.xml"/>
   <xi:include xmlns:xi="http://www.w3.org/2001/XInclude" href="java/io/InputStream.xml"/>
   <xi:include xmlns:xi="http://www.w3.org/2001/XInclude" href="java/util/jar/Manifest.xml"/>
   <constructors>
      <constructor visibility="public">
         <parameters>
            <parameter type="java.util.jar.Manifest"/>
         </parameters>
      </constructor>
      <constructor visibility="public">
         <parameters>
            <parameter type="java.io.InputStream"/>
         </parameters>
         <throws>
            <throwable type="java.io.IOException"/>
         </throws>
      </constructor>
      <constructor visibility="public"/>
   </constructors>
   <fields>
      <attr type="java.util.jar.Attributes" visibility="private"/>
      <entries type="java.util.Map" visibility="private"/>
   </fields>
   <methods>
      <equals return-type="boolean" visibility="public" overrides="true">
         <parameters>
            <parameter parameter-type="java.lang.Object"/>
         </parameters>
      </equals>
      <hashCode return-type="int" visibility="public" overrides="true"/>
      <clone return-type="java.lang.Object" visibility="public"/>
      <clear return-type="void" visibility="public"/>
      <write return-type="void" visibility="public">
         <parameters>
            <parameter parameter-type="java.io.OutputStream"/>
         </parameters>
         <throws>
            <throwable throws="java.io.IOException"/>
         </throws>
      </write>
      <toLower return-type="int" visibility="private">
         <parameters>
            <parameter parameter-type="int"/>
         </parameters>
      </toLower>
      <read return-type="void" visibility="public">
         <parameters>
            <parameter parameter-type="java.io.InputStream"/>
         </parameters>
         <throws>
            <throwable throws="java.io.IOException"/>
         </throws>
      </read>
      <getAttributes return-type="java.util.jar.Attributes" visibility="public">
         <parameters>
            <parameter parameter-type="java.lang.String"/>
         </parameters>
      </getAttributes>
      <getMainAttributes return-type="java.util.jar.Attributes" visibility="public"/>
      <getEntries return-type="java.util.Map" visibility="public"/>
      <make72Safe return-type="void" static-final="true">
         <parameters>
            <parameter parameter-type="java.lang.StringBuffer"/>
         </parameters>
      </make72Safe>
      <parseName return-type="java.lang.String" visibility="private">
         <parameters>
            <parameter parameter-type="[B"/>
            <parameter parameter-type="int"/>
         </parameters>
      </parseName>
   </methods>
</Manifest>