<?xml version="1.0" encoding="UTF-8" standalone="yes" ?>
<AccessMode class="java.nio.file.AccessMode" ref-id="126825">
   <extends class="java.lang.Enum"/>
   <xi:include xmlns:xi="http://www.w3.org/2001/XInclude" href="java/lang/Enum.xml"/>
   <xi:include xmlns:xi="http://www.w3.org/2001/XInclude" href="java/nio/file/AccessMode.xml"/>
   <xi:include xmlns:xi="http://www.w3.org/2001/XInclude" href="java/lang/String.xml"/>
   <constructors>
      <constructor visibility="private">
         <parameters>
            <parameter type="java.lang.String"/>
            <parameter type="int"/>
         </parameters>
      </constructor>
   </constructors>
   <fields>
      <READ type="java.nio.file.AccessMode" visibility="public" final="true" static-final="true"/>
      <WRITE type="java.nio.file.AccessMode" visibility="public" final="true" static-final="true"/>
      <EXECUTE type="java.nio.file.AccessMode" visibility="public" final="true" static-final="true"/>
      <_VALUES escapeSequence="0:$" type="[Ljava.nio.file.AccessMode;" visibility="private" final="true" static-final="true"/>
   </fields>
   <methods>
      <values return-type="[Ljava.nio.file.AccessMode;" visibility="public" static-final="true"/>
      <valueOf return-type="java.nio.file.AccessMode" visibility="public" static-final="true">
         <parameters>
            <parameter parameter-type="java.lang.String"/>
         </parameters>
      </valueOf>
   </methods>
</AccessMode>